theoduchamps_picsou/__init__.py
theoduchamps_picsou/picsou.py
theoduchamps_picsou/picsou_test.py
theoduchamps_picsou-0.1.0.dist-info/METADATA
theoduchamps_picsou-0.1.0.dist-info/WHEEL
theoduchamps_picsou-0.1.0.dist-info/RECORD
