Metadata-Version: 2.1
Name: theoduchamps-picsou
Version: 0.1.0
Summary: 
Author: Duchamps-Theo
Author-email: duchamps.theo2001@gmail.com
Requires-Python: >=3.10,<4.0
Classifier: Programming Language :: Python :: 3
Classifier: Programming Language :: Python :: 3.10
Classifier: Programming Language :: Python :: 3.11
Classifier: Programming Language :: Python :: 3.12
Requires-Dist: coverage (>=7.4.1,<8.0.0)
